pygifconvt_ydw/__init__.py
pygifconvt_ydw/converter.py
pygifconvt_ydw-1.0.1.dist-info/LICENSE
pygifconvt_ydw-1.0.1.dist-info/METADATA
pygifconvt_ydw-1.0.1.dist-info/WHEEL
pygifconvt_ydw-1.0.1.dist-info/top_level.txt
pygifconvt_ydw-1.0.1.dist-info/RECORD
