Metadata-Version: 2.1
Name: pygifconvt-ydw
Version: 1.0.1
Summary: Test package for distribution
Home-page: UNKNOWN
Author: dongwook
Author-email: merkur78@gmail.com
License: UNKNOWN
Keywords: GIFCONVERTER,gifconverter,ydw
Platform: UNKNOWN
Classifier: Programming Language :: Python :: 3
Classifier: License :: OSI Approved :: MIT License
Classifier: Operating System :: OS Independent
Requires-Python: >=3
License-File: LICENSE
Requires-Dist: pillow
